oakemugym/__init__.py
oakemugym/oakemuenv.py
oakemugym/registration.py
oakemugym/ui/__init__.py
oakemugym/ui/ui.py
oakemu_gymnasium-0.0.1.dist-info/LICENCE
oakemu_gymnasium-0.0.1.dist-info/METADATA
oakemu_gymnasium-0.0.1.dist-info/WHEEL
oakemu_gymnasium-0.0.1.dist-info/RECORD
