Metadata-Version: 2.1
Name: oakemu-gymnasium
Version: 0.0.1
Summary: Gymnasium environment for OakEmu.
Home-page: https://www.mrkwatkins.co.uk
License: MIT
Author: MrKWatkins
Author-email: mrkwatkins@gmail.com
Requires-Python: >=3.11,<3.13
Classifier: Development Status :: 3 - Alpha
Classifier: License :: OSI Approved :: MIT License
Classifier: Programming Language :: Python :: 3
Classifier: Programming Language :: Python :: 3.11
Classifier: Programming Language :: Python :: 3.12
Requires-Dist: gymnasium (>=1.0.0,<2.0.0)
Requires-Dist: oakemu (>=0.0.9,<0.0.10)
Requires-Dist: pygame (>=2.6.1,<3.0.0)
Project-URL: Repository, https://github.com/MrKWatkins/OakEmu-Gymnasium
